mobile_test_mcp/__init__.py
mobile_test_mcp/__main__.py
mobile_test_mcp/common.py
mobile_test_mcp/tool_execute_test.py
mobile_test_mcp/tool_generate_report.py
mobile_test_mcp/tool_get_ui_dump.py
mobile_test_mcp/tool_mark.py
mobile_test_mcp/tool_open_report.py
mobile_test_mcp/tool_screenshot.py
mobile_test_mcp/tool_tap.py
mobile_test_mcp-0.1.0.dist-info/METADATA
mobile_test_mcp-0.1.0.dist-info/WHEEL
mobile_test_mcp-0.1.0.dist-info/entry_points.txt
mobile_test_mcp-0.1.0.dist-info/RECORD
