Metadata-Version: 2.4
Name: mobile-test-mcp
Version: 0.1.0
Summary: Add your description here
Author-email: choumine <569908115@qq.com>
Requires-Python: >=3.13
Requires-Dist: mcp[cli]>=1.13.1
Requires-Dist: pillow>=11.3.0
